contextualized/__init__.py
contextualized/functions.py
contextualized/modules.py
contextualized/tests.py
contextualized/utils.py
contextualized/analysis/__init__.py
contextualized/analysis/accuracy_split.py
contextualized/analysis/bootstraps.py
contextualized/analysis/effects.py
contextualized/analysis/embeddings.py
contextualized/analysis/pvals.py
contextualized/analysis/tests.py
contextualized/baselines/__init__.py
contextualized/baselines/networks.py
contextualized/baselines/tests.py
contextualized/dags/__init__.py
contextualized/dags/graph_utils.py
contextualized/dags/lightning_modules.py
contextualized/dags/losses.py
contextualized/dags/tests.py
contextualized/dags/trainers.py
contextualized/easy/ContextualGAM.py
contextualized/easy/ContextualizedClassifier.py
contextualized/easy/ContextualizedNetworks.py
contextualized/easy/ContextualizedRegressor.py
contextualized/easy/__init__.py
contextualized/easy/tests.py
contextualized/easy/wrappers/SKLearnWrapper.py
contextualized/easy/wrappers/__init__.py
contextualized/regression/__init__.py
contextualized/regression/datasets.py
contextualized/regression/lightning_modules.py
contextualized/regression/losses.py
contextualized/regression/metamodels.py
contextualized/regression/regularizers.py
contextualized/regression/tests.py
contextualized/regression/trainers.py
contextualized_ml-0.2.9.dist-info/METADATA
contextualized_ml-0.2.9.dist-info/WHEEL
contextualized_ml-0.2.9.dist-info/licenses/LICENSE
contextualized_ml-0.2.9.dist-info/RECORD
