Metadata-Version: 2.4
Name: contextualized-ml
Version: 0.2.9
Summary: A statistical machine learning toolbox for estimating models, distributions, and functions with sample-specific parameters.
Project-URL: Homepage, https://contextualized.ml/
Project-URL: Source, https://github.com/cnellington/Contextualized/
Author-email: Caleb Ellington <cellingt@cs.cmu.edu>, Ben Lengerich <blengeri@mit.edu>
License-File: LICENSE
Keywords: contextual modeling,graphical models,machine learning,meta-learning,multitask learning
Classifier: License :: OSI Approved :: GNU General Public License v3 (GPLv3)
Classifier: Operating System :: OS Independent
Classifier: Programming Language :: Python :: 3
Requires-Python: >=3.8
Requires-Dist: igraph>=0.11.0
Requires-Dist: lightning>=2.0.0
Requires-Dist: matplotlib>=3.3.0
Requires-Dist: numpy>=1.19.0
Requires-Dist: pandas>=2.0.0
Requires-Dist: scikit-learn>=1.0.0
Requires-Dist: torch>=2.0.0
Requires-Dist: torchvision>=0.8.0
